examples/README.md
examples/__init__.py
sdk/__init__.py
sdk/ceremony.py
sdk/errors.py
sdk/gateway_client.py
sdk/nostr_utils.py
sdk/payloads.py
sdk/retry.py
sdk/solver_flows.py
sdk/types.py
sdk/wallet_utils.py
arkrelay-0.1.1.dist-info/METADATA
arkrelay-0.1.1.dist-info/WHEEL
arkrelay-0.1.1.dist-info/top_level.txt
arkrelay-0.1.1.dist-info/RECORD
