Metadata-Version: 2.4
Name: arkrelay
Version: 0.1.1
Summary: Python SDK for ArkRelay Gateway (sessions, ceremony, assets, and Nostr utilities)
Author-email: ArkRelay <dev@arkrelay.example>
License: MIT
Project-URL: Homepage, https://github.com/afeezaziz/arkrelay-gateway/tree/main/gateway/sdk-py
Project-URL: Repository, https://github.com/afeezaziz/arkrelay-gateway
Project-URL: Issues, https://github.com/afeezaziz/arkrelay-gateway/issues
Requires-Python: >=3.9
Requires-Dist: requests>=2.31.0
Requires-Dist: coincurve>=18.0.0
Requires-Dist: bech32>=1.2.0
